setup.cfg
setup.py
argdeclare/__init__.py
argdeclare/argdeclare.py
argdeclare.egg-info/PKG-INFO
argdeclare.egg-info/SOURCES.txt
argdeclare.egg-info/dependency_links.txt
argdeclare.egg-info/not-zip-safe
argdeclare.egg-info/top_level.txt