Metadata-Version: 1.0
Name: argdeclare
Version: 0.4.9
Summary: Argdeclare is a declarative argument configurator for python's argparse.
Home-page: https://github.com/ixmatus/argdeclare
Author: Parnell Springmeyer
Author-email: parnell@ixmat.us
License: Copyright (c)2013, Parnell Springmeyer
